LICENSE
README.md
setup.py
clueai/__init__.py
clueai/classify.py
clueai/client.py
clueai/embeddings.py
clueai/error.py
clueai/extract.py
clueai/generation.py
clueai/match.py
clueai/response.py
clueai/tokenize.py
clueai.egg-info/PKG-INFO
clueai.egg-info/SOURCES.txt
clueai.egg-info/dependency_links.txt
clueai.egg-info/requires.txt
clueai.egg-info/top_level.txt