Metadata-Version: 2.1
Name: clueai
Version: 0.0.1.6
Summary: A Python library for the ClueAI API
Home-page: https://github.com/clue-ai/clueai-python
Author: matrix
Author-email: brightmart@hotmail.com
License: UNKNOWN
Platform: UNKNOWN
Classifier: Programming Language :: Python :: 3
Classifier: License :: OSI Approved :: MIT License
Classifier: Operating System :: OS Independent
Requires-Python: >=3.6
